{
  "MediaMarkt main product cards": [
    {
      "href": "https://www.mediamarkt.de/de/product/_samsung-gq55q7f-qled-tv-vision-ai-smart-tv-55-zoll-138-cm-uhd-4k-smart-tv-tizen-2988691.html",
      "text": "Preisheld Gratis Standard-Lieferung Produktdatenblatt SAMSUNG GQ55Q7F QLED TV Vision AI Smart TV (Flat, 55 Zoll / 138 cm, UHD 4K, SMART TV) 613 Basierend auf 613 Bewertungen Produkttyp QLED TV Vision AI Smart TV Bildqualität UHD 4K Bildschirmdiagonale (cm/Zoll) 138 cm / 55 Zoll Betriebssystem Tizen -55% UVP 899,– € 899,00€ 399,– € 399,00€ inkl. MwSt. versandkostenfrei Bezahle in 12 Raten à 35,15 € (eff. Zins. P.a. 10,90 %)** Gesamtpreis 421,80 € Lieferung: Nur in einigen Regionen verfügbar Bitte"
    },
    {
      "href": "https://www.mediamarkt.de/de/product/_peaq-ptv-40gqf-5026t-fernseher-flat-40-zoll-1000-cm-qled-4k-smart-tv-3028407.html",
      "text": "WM-Highlight 0% Finanzierung Produktdatenblatt PEAQ PTV 40GQF-5026T QLED TV (Flat, 40 Zoll / 100 cm, Full-HD, SMART TV) 1 Basierend auf 1 Bewertungen Produkttyp QLED TV Bildqualität Full-HD Bildschirmdiagonale (cm/Zoll) 100 cm / 40 Zoll Abmessungen ohne Standfuß (BxHxT) 89.22 cm / 50.88 cm / 8.1 cm 179,– € 179,00€ inkl. MwSt. zzgl. Versand Bezahle in 10 Raten à 18,76 € (eff. Zins. P.a. 10,90 %)** Gesamtpreis 187,60 € Lieferung nach Hause Lieferung ab 24.06.2026 Abholung Bitte wähle einen Markt a"
    },
    {
      "href": "https://www.mediamarkt.de/de/product/_samsung-gu98du9079u-led-tv-flat-98-zoll-249-cm-uhd-4k-smart-tv-tizen-2924386.html",
      "text": "Inkl. Streaming Content Gratis Standard-Lieferung Produktdatenblatt SAMSUNG GU98DU9079U LED TV (Flat, 98 Zoll / 249 cm, UHD 4K, SMART TV, Tizen) 735 Basierend auf 735 Bewertungen Produkttyp LED TV Bildqualität UHD 4K Bildschirmdiagonale (cm/Zoll) 249 cm / 98 Zoll Abmessungen ohne Standfuß (BxHxT) 2181.1 mm / 1244.1 mm / 63.5 mm -67% UVP 4299,– € 4299,00€ 1399,– € 1399,00€ inkl. MwSt. versandkostenfrei Bezahle in 48 Raten à 35,74 € (eff. Zins. P.a. 10,90 %)** Gesamtpreis 1715,52 € Lieferung nach "
    },
    {
      "href": "https://www.mediamarkt.de/de/product/_philips-55pus8550-led-tv-flat-55-zoll-139-cm-uhd-4k-smart-tv-ambilight-2982237.html",
      "text": "Gratis Standard-Lieferung Gewinnspiel Produktdatenblatt PHILIPS 55PUS8550/12 LED Ambilight TV (Flat, 55 Zoll / 139 cm, UHD 4K, SMART TV, Ambilight) 354 Basierend auf 354 Bewertungen Produkttyp LED Ambilight TV Bildqualität UHD 4K Bildschirmdiagonale (cm/Zoll) 139 cm / 55 Zoll Betriebssystem Titan OS -50% UVP 899,– € 899,00€ 444,– € 444,00€ inkl. MwSt. versandkostenfrei Bezahle in 18 Raten à 26,74 € (eff. Zins. P.a. 10,90 %)** Gesamtpreis 481,32 € Lieferung: Nur in einigen Regionen verfügbar Bitt"
    },
    {
      "href": "https://www.mediamarkt.de/de/product/_kiano-slim-tv-32-smart-tv-flat-32-zoll-80-cm-hd-ready-134332261.html",
      "text": "WM-Highlight Produktdatenblatt KIANO Slim TV 32 Fernseher (Flat, 32 Zoll / 81,28 cm, HD) 11 Basierend auf 11 Bewertungen Produkttyp Fernseher Bildqualität HD Bildschirmdiagonale (cm/Zoll) 81.28 cm / 32 Zoll Bildwiederholungsfrequenz 60 Hz -20% Tiefstpreis (30 Tage): 125,90 € 125,90€ 99,90 € 99,90€ inkl. MwSt. versandkostenfrei Verkauf und Versand durch 7Way Lieferung nach Hause Lieferung ab 25.06.2026 Vergleichen In den Warenkorb In den Warenkorb"
    }
  ],
  "OTTO main product cards": [
    {
      "article_number": "96406113",
      "product_id": "C1980401029",
      "variation_id": "1980401030",
      "list_position": "1",
      "origin": "sponsored",
      "href": "https://www.otto.de/p/philips-65pus7000-12-led-fernseher-164-cm-65-zoll-4k-ultra-hd-smart-tv-pixel-precise-uhd-hdr10plus-dolby-atmos-dts-x-sound-gaming-C1980401029/",
      "text": "gesponsert Philips 65PUS7000/12 LED-Fernseher 164 cm/65 Zoll Diagonale LED Bildschirmtechnologie 4K Ultra HD Auflösung Produktdatenblatt (28) 449,00 € UVP 949,00 € nur für kurze Zeit 16,11 € mtl. in 36 Raten -53% in 1-2 Werktagen bei dir"
    },
    {
      "article_number": "78173651",
      "product_id": "1968874107",
      "variation_id": "1968874108",
      "list_position": "2",
      "origin": "sponsored",
      "href": "https://www.otto.de/p/lg-oled48b59la-oled-fernseher-121-cm-48-zoll-4k-ultra-hd-smart-tv-1968874107/",
      "text": "Sehr beliebt gesponsert LG OLED48B59LA OLED-Fernseher 121 cm/48 Zoll Diagonale OLED Bildschirmtechnologie 4K Ultra HD Auflösung Produktdatenblatt (21) 599,00 € UVP 1.699,00 € nur für kurze Zeit 17,39 € mtl. in 48 Raten -65% in 1-2 Werktagen bei dir"
    },
    {
      "article_number": "56104054",
      "product_id": "C2000548368",
      "variation_id": "2000548369",
      "list_position": "3",
      "origin": null,
      "href": "https://www.otto.de/p/philips-32phs6000-12-led-fernseher-80-cm-32-zoll-hd-ready-smart-tv-pixel-plus-hd-hdr10-hlg-dolby-audio-vocal-boost-C2000548368/",
      "text": "Sehr beliebt Philips 32PHS6000/12 LED-Fernseher 80 cm/32 Zoll Diagonale LED Bildschirmtechnologie HD ready Auflösung Produktdatenblatt (297) ab 139,00 € UVP 299,00 € nur für kurze Zeit 12,70 € mtl. in 12 Raten -54% in 1-2 Werktagen bei dir"
    },
    {
      "article_number": "10666503",
      "product_id": "1995107347",
      "variation_id": "1995107348",
      "list_position": "4",
      "origin": null,
      "href": "https://www.otto.de/p/samsung-gq55q6faau-qled-fernseher-138-cm-55-zoll-4k-ultra-hd-smart-tv-1995107347/",
      "text": "Sehr beliebt Samsung GQ55Q6FAAU QLED-Fernseher 138 cm/55 Zoll Diagonale QLED Bildschirmtechnologie 4K Ultra HD Auflösung Produktdatenblatt (316) 399,00 € UVP 849,00 € nur für kurze Zeit 19,82 € mtl. in 24 Raten -53% in 1-2 Werktagen bei dir"
    },
    {
      "article_number": "94362409",
      "product_id": "1975568002",
      "variation_id": "1975568003",
      "list_position": "5",
      "origin": null,
      "href": "https://www.otto.de/p/samsung-gu65u7099fu-led-fernseher-163-cm-65-zoll-4k-ultra-hd-smart-tv-crystal-uhd-q-symphony-dolby-surround-sound-triple-tuner-smart-hub-1975568002/",
      "text": "Sehr beliebt Samsung GU65U7099FU LED-Fernseher 163 cm/65 Zoll Diagonale LED Bildschirmtechnologie 4K Ultra HD Auflösung Produktdatenblatt (243) 439,99 € UVP 899,00 € 15,79 € mtl. in 36 Raten -51% in 1-2 Werktagen bei dir"
    }
  ],
  "OTTO jsonld_product_count": 18,
  "Amazon main result cards": [
    {
      "asin": "B0CQMWQDH4",
      "index": "3",
      "href": null,
      "text": "Featured from Amazon brands Featured from Amazon brands Amazon Fire TV Stick HD, free and live TV, Alexa Voice Remote, smart home controls, HD streaming #1 Top-Rated 4.6 4.6 out of 5 stars (64.1K) 5K+ bought in past month Price, product page €44.99 € 44 . 99 FREE delivery Sat 27 Jun on eligible first order Add to basket"
    },
    {
      "asin": "B0DFNM3XZ9",
      "index": "4",
      "href": null,
      "text": "Featured from Amazon brands Featured from Amazon brands Amazon Ember 55\" 4-Series with Fire TV (newest gen), 4K Ultra HD smart TV with Alexa Remote, HDR10+, fast processor, Dolby Audio, Ambient Experience, free and live TV 4.5 4.5 out of 5 stars (195) 100+ bought in past month Prime Day Deal Price, product page €349.99 € 349 . 99 RRP: €699.99 RRP: €699.99 €699.99 Exclusive Prime price See options G A G Product Sheet Energy Efficiency Product Sheet"
    },
    {
      "asin": "B0CZWNDNXW",
      "index": "5",
      "href": "https://www.amazon.de/-/en/Hisense-43E6NT-Precision-Colour-Bluetooth/dp/B0CZWNDNXW/ref=sr_1_3?dib=eyJ2IjoiMSJ9.otqw8B-xLHqcVBPNg98efY3qBGrUIPRUb471VF_TBB0wAeCFTfSYIGZu5mQ3bipMHshto6rZt5i8WD_rkE0uxdHfdJixGx4q0kx-AvUkrduPXxP_Yia6Scpgsas6_u4wqWmRVmQ9BuhUjHa0vi_gubbqZFEn293ZHo1dtrb-B73vo1DSHSY34ZdvwB6uR6KOVnkWg9Vjb9oxmcHNVyoUibwXXZJ9vdOpLFfTMV7Oz0I.aCUpeuEhuMRjfBfbmekYxqiJK-A1ogoOS6unAcKax68&dib_tag=se&keywords=fernseher&qid=1782199317&sr=8-3",
      "text": "Amazon's Choice for \"fernseher\" Hisense 43E6NT 108 cm (43 Inch) TV, 4K UHD Smart TV, Precision Colour, HDR, Dolby Vision, 60Hz, Triple Tuner DVB-C/S/S2/T/T2, WiFi, HDMI 2.1, Bluetooth, Alexa Built-in, Black, [2024] Options: 9 sizes 4.4 4.4 out of 5 stars (4.3K) 1K+ bought in past month Price, product page €199.00 € 199 . 00 RRP: €269.99 RRP: €269.99 €269.99 FREE delivery Fri 26 Jun Service: TV Collection Add to basket More buying choices €169.15 (3+ used & new offers) E A G Product Sheet Energy "
    },
    {
      "asin": "B0F5BSYQGZ",
      "index": "7",
      "href": "https://www.amazon.de/-/en/Samsung-Optimised-Processor-Upscaling-SmartThings/dp/B0F5BSYQGZ/ref=sr_1_4?dib=eyJ2IjoiMSJ9.otqw8B-xLHqcVBPNg98efY3qBGrUIPRUb471VF_TBB0wAeCFTfSYIGZu5mQ3bipMHshto6rZt5i8WD_rkE0uxdHfdJixGx4q0kx-AvUkrduPXxP_Yia6Scpgsas6_u4wqWmRVmQ9BuhUjHa0vi_gubbqZFEn293ZHo1dtrb-B73vo1DSHSY34ZdvwB6uR6KOVnkWg9Vjb9oxmcHNVyoUibwXXZJ9vdOpLFfTMV7Oz0I.aCUpeuEhuMRjfBfbmekYxqiJK-A1ogoOS6unAcKax68&dib_tag=se&keywords=fernseher&qid=1782199317&sr=8-4",
      "text": "Samsung Crystal UHD 4K U7099F 65 Inch (163 cm) LED TV, Optimised for Football and Gaming, Crystal Processor 4K, AI Upscaling, SmartThings, Knox Security, Free Content, Smart AI TV Options: 6 sizes 4.3 4.3 out of 5 stars (1K) 1K+ bought in past month Price, product page €439.00 € 439 . 00 RRP: €586.78 RRP: €586.78 €586.78 FREE delivery Fri 26 Jun Service: TV Collection Add to basket More buying choices €373.15 (2 used & new offers) G A G Product Sheet Energy Efficiency Product Sheet Resolution : "
    },
    {
      "asin": "B0F5BR3WSK",
      "index": "13",
      "href": "https://www.amazon.de/-/en/Samsung-Optimised-Processor-Upscaling-SmartThings/dp/B0F5BR3WSK/ref=sr_1_5?dib=eyJ2IjoiMSJ9.otqw8B-xLHqcVBPNg98efY3qBGrUIPRUb471VF_TBB0wAeCFTfSYIGZu5mQ3bipMHshto6rZt5i8WD_rkE0uxdHfdJixGx4q0kx-AvUkrduPXxP_Yia6Scpgsas6_u4wqWmRVmQ9BuhUjHa0vi_gubbqZFEn293ZHo1dtrb-B73vo1DSHSY34ZdvwB6uR6KOVnkWg9Vjb9oxmcHNVyoUibwXXZJ9vdOpLFfTMV7Oz0I.aCUpeuEhuMRjfBfbmekYxqiJK-A1ogoOS6unAcKax68&dib_tag=se&keywords=fernseher&qid=1782199317&sr=8-5",
      "text": "Samsung Crystal UHD 4K U7099F 43 Inch (108 cm) LED TV, Optimised for Football and Gaming, Crystal Processor 4K, AI Upscaling, SmartThings, Knox Security, Free Content, Smart AI TV Options: 6 sizes 4.3 4.3 out of 5 stars (1K) 1K+ bought in past month Prime Day Deal Price, product page €245.00 € 245 . 00 RRP: €330.74 RRP: €330.74 €330.74 Exclusive Prime price See options G A G Product Sheet Energy Efficiency Product Sheet Resolution : 4K Display Size : 43 inches Display Type : Crystal UHD Refresh "
    },
    {
      "asin": "B0F4548TCQ",
      "index": "14",
      "href": "https://www.amazon.de/-/en/Xiaomi-Smart-Triple-Tuner-Virtual/dp/B0F4548TCQ/ref=sr_1_6?dib=eyJ2IjoiMSJ9.otqw8B-xLHqcVBPNg98efY3qBGrUIPRUb471VF_TBB0wAeCFTfSYIGZu5mQ3bipMHshto6rZt5i8WD_rkE0uxdHfdJixGx4q0kx-AvUkrduPXxP_Yia6Scpgsas6_u4wqWmRVmQ9BuhUjHa0vi_gubbqZFEn293ZHo1dtrb-B73vo1DSHSY34ZdvwB6uR6KOVnkWg9Vjb9oxmcHNVyoUibwXXZJ9vdOpLFfTMV7Oz0I.aCUpeuEhuMRjfBfbmekYxqiJK-A1ogoOS6unAcKax68&dib_tag=se&keywords=fernseher&qid=1782199317&sr=8-6",
      "text": "Best Seller in TVs Xiaomi TV F 32 32\" HD Smart TV Fire OS7 Triple Tuner DVB-C/S/S2/T/T2, Dolby Audio, DTS Virtual:X, DTS-HD, Voice Control with Alexa, Compatible with Apple AirPlay Options: 5 sizes 4.3 4.3 out of 5 stars (5.9K) 2K+ bought in past month Prime Day Deal Price, product page €126.60 € 126 . 60 RRP: €149.00 RRP: €149.00 €149.00 Exclusive Prime price See options F A G Product Sheet Energy Efficiency Product Sheet Resolution : 720p Display Size : 32 inches Display Type : VA Refresh Rate"
    },
    {
      "asin": "B0DFNWC8PW",
      "index": "15",
      "href": "https://www.amazon.de/-/en/fire-tv-4-series/dp/B0DFNWC8PW/ref=sr_1_7?dib=eyJ2IjoiMSJ9.otqw8B-xLHqcVBPNg98efY3qBGrUIPRUb471VF_TBB0wAeCFTfSYIGZu5mQ3bipMHshto6rZt5i8WD_rkE0uxdHfdJixGx4q0kx-AvUkrduPXxP_Yia6Scpgsas6_u4wqWmRVmQ9BuhUjHa0vi_gubbqZFEn293ZHo1dtrb-B73vo1DSHSY34ZdvwB6uR6KOVnkWg9Vjb9oxmcHNVyoUibwXXZJ9vdOpLFfTMV7Oz0I.aCUpeuEhuMRjfBfbmekYxqiJK-A1ogoOS6unAcKax68&dib_tag=se&keywords=fernseher&qid=1782199317&sr=8-7",
      "text": "Amazon Ember 50\" 4-Series with Fire TV (newest gen), 4K Ultra HD smart TV with Alexa Remote, HDR10+, fast processor, Dolby Audio, Ambient Experience, free and live TV 4.5 4.5 out of 5 stars (195) 200+ bought in past month Prime Day Deal Price, product page €289.99 € 289 . 99 RRP: €599.99 RRP: €599.99 €599.99 Exclusive Prime price See options F A G Product Sheet Energy Efficiency Product Sheet"
    },
    {
      "asin": "B0F75D5GTM",
      "index": "16",
      "href": null,
      "text": "Featured from Amazon brands Featured from Amazon brands Amazon Ember 32\" 2-Series with Fire TV (newest gen), HD smart TV with Alexa Remote, fast streaming, Dolby Audio, Ambient Experience, free and live TV 4.4 4.4 out of 5 stars (146) 200+ bought in past month Prime Day Deal Price, product page €144.99 € 144 . 99 RRP: €279.99 RRP: €279.99 €279.99 Exclusive Prime price See options F A G Product Sheet Energy Efficiency Product Sheet"
    }
  ]
}